ducktape/__init__.py
ducktape/__main__.py
ducktape/errors.py
ducktape/json_serializable.py
ducktape/template.py
ducktape/cluster/__init__.py
ducktape/cluster/cluster.py
ducktape/cluster/cluster_spec.py
ducktape/cluster/finite_subcluster.py
ducktape/cluster/json.py
ducktape/cluster/linux_remoteaccount.py
ducktape/cluster/localhost.py
ducktape/cluster/node_container.py
ducktape/cluster/remoteaccount.py
ducktape/cluster/vagrant.py
ducktape/cluster/windows_remoteaccount.py
ducktape/command_line/__init__.py
ducktape/command_line/defaults.py
ducktape/command_line/main.py
ducktape/command_line/parse_args.py
ducktape/mark/__init__.py
ducktape/mark/_mark.py
ducktape/mark/mark_expander.py
ducktape/mark/resource.py
ducktape/services/__init__.py
ducktape/services/background_thread.py
ducktape/services/service.py
ducktape/services/service_registry.py
ducktape/templates/report/report.css
ducktape/templates/report/report.html
ducktape/tests/__init__.py
ducktape/tests/event.py
ducktape/tests/loader.py
ducktape/tests/loggermaker.py
ducktape/tests/reporter.py
ducktape/tests/result.py
ducktape/tests/runner.py
ducktape/tests/runner_client.py
ducktape/tests/scheduler.py
ducktape/tests/serde.py
ducktape/tests/session.py
ducktape/tests/status.py
ducktape/tests/test.py
ducktape/utils/__init__.py
ducktape/utils/http_utils.py
ducktape/utils/local_filesystem_utils.py
ducktape/utils/persistence.py
ducktape/utils/terminal_size.py
ducktape/utils/util.py
systests/__init__.py
systests/cluster/__init__.py
systests/cluster/test_debug.py
systests/cluster/test_no_cluster.py
systests/cluster/test_remote_account.py
systests/cluster/test_runner_operations.py
tests/__init__.py
tests/ducktape_mock.py
tests/test_utils.py
tests/cluster/__init__.py
tests/cluster/check_cluster.py
tests/cluster/check_cluster_spec.py
tests/cluster/check_finite_subcluster.py
tests/cluster/check_json.py
tests/cluster/check_localhost.py
tests/cluster/check_node_container.py
tests/cluster/check_remoteaccount.py
ducktape-0.13.0.dist-info/METADATA
ducktape-0.13.0.dist-info/WHEEL
ducktape-0.13.0.dist-info/entry_points.txt
ducktape-0.13.0.dist-info/top_level.txt
ducktape-0.13.0.dist-info/RECORD
